hxz_pandora/__init__.py
hxz_pandora/__main__.py
hxz_pandora/cloud_launcher.py
hxz_pandora/launcher.py
hxz_pandora/py.typed
hxz_pandora/bots/__init__.py
hxz_pandora/bots/legacy.py
hxz_pandora/bots/server.py
hxz_pandora/exts/__init__.py
hxz_pandora/exts/config.py
hxz_pandora/exts/hooks.py
hxz_pandora/exts/token.py
hxz_pandora/flask/static/apple-touch-icon.png
hxz_pandora/flask/static/favicon-16x16.png
hxz_pandora/flask/static/favicon-32x32.png
hxz_pandora/flask/static/_next/static/chunks/113-23682f80a24dd00d.js
hxz_pandora/flask/static/_next/static/chunks/14-0cb0d20affbd720d.js
hxz_pandora/flask/static/_next/static/chunks/174-bd28069f281ef76f.js
hxz_pandora/flask/static/_next/static/chunks/1f110208-44a6f43ddc5e9011.js
hxz_pandora/flask/static/_next/static/chunks/264-13e92c51b0315184.js
hxz_pandora/flask/static/_next/static/chunks/360-442b869f1ba4bb1b.js
hxz_pandora/flask/static/_next/static/chunks/424-d1d3bfe6a3ca6c4a.js
hxz_pandora/flask/static/_next/static/chunks/554.9b8bfd0762461d74.js
hxz_pandora/flask/static/_next/static/chunks/68a27ff6-1185184b61bc22d0.js
hxz_pandora/flask/static/_next/static/chunks/762-222df1028c0c1555.js
hxz_pandora/flask/static/_next/static/chunks/949.1a6eb804b5e91f61.js
hxz_pandora/flask/static/_next/static/chunks/bd26816a-981e1ddc27b37cc6.js
hxz_pandora/flask/static/_next/static/chunks/framework-7a789ee31d2a7534.js
hxz_pandora/flask/static/_next/static/chunks/main-149b337e061b4d04.js
hxz_pandora/flask/static/_next/static/chunks/polyfills-c67a75d1b6f99dc8.js
hxz_pandora/flask/static/_next/static/chunks/webpack-c9a868e8e0796ec6.js
hxz_pandora/flask/static/_next/static/chunks/pages/_app-aaa11de1926dcafe.js
hxz_pandora/flask/static/_next/static/chunks/pages/_error-786d27d84962122a.js
hxz_pandora/flask/static/_next/static/chunks/pages/chat/[[...chatId]]-76751174916fa3f8.js
hxz_pandora/flask/static/_next/static/css/ac221fb2caad35a6.css
hxz_pandora/flask/static/_next/static/olf4sv64FWIcQ_zCGl90t/_buildManifest.js
hxz_pandora_ChatGPT-1.0.4.dist-info/LICENSE
hxz_pandora_ChatGPT-1.0.4.dist-info/METADATA
hxz_pandora_ChatGPT-1.0.4.dist-info/WHEEL
hxz_pandora_ChatGPT-1.0.4.dist-info/entry_points.txt
hxz_pandora_ChatGPT-1.0.4.dist-info/top_level.txt
hxz_pandora_ChatGPT-1.0.4.dist-info/RECORD
